exopy/__init__.py
exopy/data_loader.py
exopy/generator/__init__.py
exopy/generator/_erikson_dinucl_shuffle.py
exopy/generator/_sequence.py
exopy/models/.ipynb_checkpoints/_losses-checkpoint.py
exopy/models/__init__.py
exopy/models/_base.py
exopy/models/_base_modules.py
exopy/models/_constants.py
exopy/models/_data.py
exopy/models/_deepbind.py
exopy/models/_exo_cnn.py
exopy/models/_exo_fcn.py
exopy/models/_exo_gru.py
exopy/models/_exo_lstm.py
exopy/models/_model.py
exopy/models/_module.py
exopy/models/_utils.py
exopy/plotting.py
exopy/postprocessing/__init__.py
exopy/postprocessing/interpretability.py
exopy/postprocessing/pfm.py
exopy/preprocessing/__init__.py
exopy/utils.py
exosomians-0.1.1.dist-info/METADATA
exosomians-0.1.1.dist-info/WHEEL
exosomians-0.1.1.dist-info/RECORD
