Metadata-Version: 2.1
Name: exosomians
Version: 0.1.1
Summary: ExoPy python package
Author: Ali Saberi
Author-email: saberiato@gmail.com
Requires-Python: >=3.9,<4.0
Classifier: Programming Language :: Python :: 3
Classifier: Programming Language :: Python :: 3.9
Classifier: Programming Language :: Python :: 3.10
Classifier: Programming Language :: Python :: 3.11
Requires-Dist: numpy (==1.23.4)
Requires-Dist: pytorch-lightning (==1.5.4)
Requires-Dist: scanpy (>=1.9.3,<2.0.0)
Requires-Dist: torch (>=2.0.0,<3.0.0)
